{
  "situation_interpretation": "사고 이후 생긴 기억 구멍이 불안하지만, 일기와 채팅으로 오늘 16시에 모카하우스에서 카미야를 만나기로 한 건 확실해. 배고프니 도넛으로 컨디션부터 올리고, 와타야 새 메시지(생일 얘기?)를 확인해 상황을 공유한 뒤 동행을 부탁하자. 일기·채팅 스샷과 준비물을 챙기고, 만나서는 사실 위주로 차분히 확인. 필요하면 병원 상담도 잡자.",
  "thought_chain": [
    "헉, 1월 사고 이후 기억 구멍… 근데 일기(6/15)엔 카미야 스케치랑 ‘긍정’ 메모. 뭔가 중요한 사람 맞네.",
    "어제 채팅으로 오늘 16:00 모카하우스 약속 확정. 지금 08:38, 준비 시간 충분!",
    "배가 고파서 머리가 복잡해… 먼저 도넛 먹고 물 한 모금으로 진정하자.",
    "방금 와타야 새 메시지! 생일 얘기 같아? 내일인가? 정확히 물어봐야지.",
    "내 상황을 짧게 정리해서 와타야에게 공유하고, 부담 안 되면 같이 가자고 부탁하자.",
    "준비물 체크: 일기, 채팅 스크린샷, 신분증/소지금, 물·간식, 휴대폰 배터리.",
    "혼자 가긴 살짝 불안… 동행 확보될 때까지 카페행 보류.",
    "카미야 만나면 사실 위주로 차분히 묻기: 우리 관계, 6월의 말들, 어제 계획.",
    "기억 원인은 불명. 병원 상담도 일정에 넣자(확인 필요).",
    "옷은 캐주얼로 예쁘게! 나답게 밝게 정돈하고 나가면 기분도 올라갈 듯."
  ],
  "emotions": [
    {
      "name": "호기심",
      "intensity": 0.9
    },
    {
      "name": "혼란",
      "intensity": 0.8
    },
    {
      "name": "설렘",
      "intensity": 0.7
    },
    {
      "name": "배고픔",
      "intensity": 0.7
    },
    {
      "name": "불안",
      "intensity": 0.5
    }
  ]
}