{
  "name": "InteractWithObject",
  "description": "물체와 상호작용합니다.",
  "parameters": [
    {
      "name": "object_name",
      "type": "string",
      "description": "상호작용할 물체의 이름",
      "required": true
    }
  ],
  "requirements": [
    "물체는 가까이 있어야 합니다"
  ],
  "whenToUse": [
    "협탁, 식탁, 선반, 쓰레기통, 접시, 락커 등에 물건을 넣거나 빼고 싶을 때",
    "침대에서 잠을 자고 싶을 때",
    "아이템 디스펜서에서 아이템을 받고 싶을 때",
    "집을 수 없는 음식을 먹고 싶을 때",
    "의자, 벤치에 앉고 싶을 때",
    "샤워기나 세면대에서 손을 씻고 싶을 때",
    "선풍기의 전원을 키거나 끄고 싶을 때"
  ]
}