{
  "entries": [
    {
      "timestamp": "2025-01-12T15:00:00Z",
      "type": "event_occurred",
      "content": "차가 매우 빠르게 다가와 부딪침",
      "details": "위치: 신주쿠:가부키초:1-chome-6",
      "emotions": {}
    },
    {
      "timestamp": "2025-02-23T07:00:00Z",
      "type": "wake up",
      "content": "도쿄:세타가와:미나미 카라스야마:5-chome-13:히노의 집:거실에서 일어남",
      "details": "체력 조금 회복",
      "emotions": {}
    },
    {
      "timestamp": "2025-02-23T07:00:00Z",
      "type": "perception",
      "content": "상황 인식: 어제 사고로 경계가 높아. 우선 노트 한 번 읽고 몸 상태 확인, 도넛 먹은 뒤 아이폰 알림 확인.",
      "details": "생각 체인: 으으… 아직도 어제 신주쿠에서 차가 빠르게 다가온 그 장면이 등골에 남아있어. 경계심이 팽팽하네. -> 아침엔 무조건 노트부터 읽어야 해 — 이건 내 루틴이니까, 안 그러면 기분이 엉망이 돼. -> 근데 몸 상태도 금방 확인해야겠어. 출혈이나 통증, 어지러움 같은 건 없는지 손으로 툭툭 살펴보자. -> 협탁에 아이폰 알림이 ‘카미야’로 와있다... 누군지 기억 안 나서 궁금하긴 한데, 너무 성급하게 반응하면 찜찜해. -> 식탁에 도넛 세 개가 반짝반짝… 배고프니까 하나 먹으면 머리도 좀 맑아질 것 같아. 아, 달콤한 건 항상 옳지! -> 타협안: 우선 노트 한 번 빨리 훑어서 아침 루틴을 지키고(짧게!), 바로 이어서 간단한 신체 점검을 한다. -> 그다음 도넛 한 개랑 물 한 컵으로 배고픔·긴장 완화. 에너지 좀 채우고나서 아이폰 알림을 확인하자. -> 메시지는 바로 함부로 링크 클릭 안 하고 내용만 확인한 뒤 발신자 번호 검색하거나 친구에게 물어보는 게 안전하겠어. -> 오늘 저녁엔 노트에 사고와 증상, 감정도 간단히 기록해야지 — 안 그러면 불안이 자꾸 커질 거야. -> 자, 재빨리 하자! 장난기도 살짝 남겨두면서 약삭빠르게 처리하면 괜찮을 거야.",
      "emotions": {
        "경계": 0.9,
        "호기심": 0.8,
        "불안": 0.6,
        "안도": 0.6,
        "배고픔": 0.6
      }
    },
    {
      "timestamp": "2025-02-23T07:01:00Z",
      "type": "thinking",
      "content": "이동을(를) 하기로 결정했다.",
      "details": "의도: 노트부터 재빨리 훑을 거야 — 짧게! 핵심만 읽고 바로 몸 상태 툭툭 점검하자. 그다음 도넛 하나랑 물 마시고 아이폰 알림 천천히 확인할 테니, 링크 함부로 누르지 말자~ 히노, 약삭빠르게 처리하자고!",
      "emotions": {}
    },
    {
      "timestamp": "2025-02-23T07:01:00Z",
      "type": "action_start",
      "content": "이동을(를) 시작했다.",
      "details": "파라미터: {\"entity_name\":\"협탁:히노의 일기\"}",
      "emotions": {}
    },
    {
      "timestamp": "2025-02-23T07:02:00Z",
      "type": "action_complete",
      "content": "이동을(를) 완료했다.",
      "details": "파라미터: {\"entity_name\":\"협탁:히노의 일기\"}, 성공 여부: True",
      "emotions": {}
    },
    {
      "timestamp": "2025-02-23T07:03:00Z",
      "type": "perception",
      "content": "상황 인식: 어제 사고로 경계 높음. 노트 훑기→몸 점검→도넛 1개+물로 안정→아이폰 메시지 안전 확인(이상시 병원).",
      "details": "생각 체인: 으으… 어제 신주쿠에서 차가 빠르게 다가온 장면이 자꾸 떠올라, 등골이 찌릿—경계심 팽팽해. -> 일단 루틴! 아침 노트는 꼭 읽어야 마음이 조금 정리돼, 1분만! 핵심만 훑자. -> 노트 훑은 직후 바로 몸을 툭툭: 출혈·멍·심한 통증·어지러움·구토 같은 이상 신호 없는지 확인. -> 식탁의 도넛 세 개가 반짝이는데, 지금 당장 세 개 다 먹고픈 충동이야—하지만 속이 더 불편해질 수 있으니 하나만. -> 도넛 한 입과 물 한 컵으로 당 보충하고 안정 찾자, 아침에 배고프면 판단이 흐려지니까 조심. -> 아이폰 알림 '카미야'는 낯선 이름이니 링크나 첨부 파일 절대 클릭 금지, 내용만 읽고 번호나 친구에게 확인. -> 몸에 이상 증상 있으면 곧바로 병원으로—뇌진탕이나 내부 출혈 같은 지연 증상 가능성 생각해 두자. -> 오늘 저녁엔 일기에 사고 경위·신체 증상·감정 정리해서 불안 확산을 막자, 이건 약속! -> 즉흥적인 장난끼가 올라오지만, 약삭빠르게 순서를 지켜서 안전부터 확보하자 — 노트→몸점검→도넛·물→아이폰 확인. -> 조금은 장난치고 싶지만, 오늘은 멋대로 굴기보다 신중하게 굴어야 해. 그래도 웃음은 잊지 말자, 히노 스타일로!",
      "emotions": {
        "경계": 0.9,
        "호기심": 0.8,
        "불안": 0.6,
        "배고픔": 0.6,
        "안도": 0.6
      }
    },
    {
      "timestamp": "2025-02-23T07:04:00Z",
      "type": "thinking",
      "content": "물건과 상호작용을(를) 하기로 결정했다.",
      "details": "의도: 협탁에 있는 히노의 일기를 재빨리 쓱 훑어 핵심만 읽고 감정을 정리해 불안을 낮추겠다. 그 후 계획대로 신체 자가점검→도넛+물→아이폰 메시지 안전 확인 순으로 진행할 준비를 하겠다.",
      "emotions": {}
    },
    {
      "timestamp": "2025-02-23T07:04:00Z",
      "type": "action_start",
      "content": "물건과 상호작용을(를) 시작했다.",
      "details": "파라미터: {\"object_name\":\"협탁\"}",
      "emotions": {}
    },
    {
      "timestamp": "2025-02-23T07:05:00Z",
      "type": "action_complete",
      "content": "물건과 상호작용을(를) 완료했다.",
      "details": "파라미터: {\"object_name\":\"협탁\"}, 성공 여부: True",
      "emotions": {}
    },
    {
      "timestamp": "2025-02-23T07:06:00Z",
      "type": "thinking",
      "content": "생각을(를) 하기로 결정했다.",
      "details": "의도: 재빨리 자기 신체 상태 자가점검을 해서 출혈·멍·심한 통증·어지러움·구토 등의 이상 유무를 확인하고, 이상 발견 시 병원 행을 결정할 근거를 마련한다. 점검이 문제 없으면 바로 도넛+물로 안정한 뒤 아이폰 메시지 확인으로 넘어간다.",
      "emotions": {}
    },
    {
      "timestamp": "2025-02-23T07:06:00Z",
      "type": "action_start",
      "content": "생각을(를) 시작했다.",
      "details": "파라미터: {\"think_scope\":\"current_analysis\",\"topic\":\"어제 신주쿠 사고 관련 신체 자가점검: 출혈·멍·심한 통증·어지러움·구토 여부 빠르게 확인하고, 이상 발견 시 즉시 병원행 결정(증상 기록 포함)\",\"duration\":35}",
      "emotions": {}
    }
  ],
  "lastUpdated": "2025-02-23T07:06:00Z"
}